pipen_filters/__init__.py
pipen_filters/filters.py
pipen_filters-1.1.2.dist-info/METADATA
pipen_filters-1.1.2.dist-info/WHEEL
pipen_filters-1.1.2.dist-info/entry_points.txt
pipen_filters-1.1.2.dist-info/RECORD
